mormorsql/__init__.py
mormorsql/dfsql.py
mormorsql-0.1.dist-info/LICENSE
mormorsql-0.1.dist-info/METADATA
mormorsql-0.1.dist-info/WHEEL
mormorsql-0.1.dist-info/top_level.txt
mormorsql-0.1.dist-info/RECORD
